pyproject.toml
setup.py
ohl/__init__.py
ohl/main.py
ohl/tree.py
ohl.egg-info/PKG-INFO
ohl.egg-info/SOURCES.txt
ohl.egg-info/dependency_links.txt
ohl.egg-info/entry_points.txt
ohl.egg-info/requires.txt
ohl.egg-info/top_level.txt