Metadata-Version: 2.1
Name: ohl
Version: 0.0.1
Requires-Python: >=3.10
Requires-Dist: textual>=0.71.0
